rmops/__init__.py
rmops/email/__init__.py
rmops/sftp/__init__.py
rmops/ssh/__init__.py
rmops-0.1.0.dist-info/METADATA
rmops-0.1.0.dist-info/WHEEL
rmops-0.1.0.dist-info/top_level.txt
rmops-0.1.0.dist-info/RECORD
